pyspartn/__init__.py
pyspartn/_version.py
pyspartn/exceptions.py
pyspartn/socket_wrapper.py
pyspartn/spartnhelpers.py
pyspartn/spartnmessage.py
pyspartn/spartnreader.py
pyspartn/spartntables.py
pyspartn/spartntypes_core.py
pyspartn/spartntypes_get.py
pyspartn-1.0.8.dist-info/licenses/LICENSE
pyspartn-1.0.8.dist-info/METADATA
pyspartn-1.0.8.dist-info/WHEEL
pyspartn-1.0.8.dist-info/top_level.txt
pyspartn-1.0.8.dist-info/RECORD
